[
  {
    "timestamp": 1780871827303,
    "embeds": [
      {
        "title": "Fjord (m +3)",
        "description": "No description provided",
        "author": {
          "name": "Frogt007",
          "url": "https://alter-ego.fandom.com/wiki/Special:Contribs/Frogt007"
        },
        "fields": [
          {
            "name": "Tags",
            "value": "Source edit",
            "inline": false
          }
        ],
        "color": 35840
      }
    ]
  },
  {
    "timestamp": 1780871712860,
    "embeds": [
      {
        "title": "Whistle (m 0)",
        "description": "No description provided",
        "author": {
          "name": "Frogt007",
          "url": "https://alter-ego.fandom.com/wiki/Special:Contribs/Frogt007"
        },
        "fields": [
          {
            "name": "Tags",
            "value": "Source edit",
            "inline": false
          }
        ],
        "color": 8750469
      }
    ]
  },
  {
    "timestamp": 1780871698190,
    "embeds": [
      {
        "title": "Whistle (m +20)",
        "description": "No description provided",
        "author": {
          "name": "Frogt007",
          "url": "https://alter-ego.fandom.com/wiki/Special:Contribs/Frogt007"
        },
        "fields": [
          {
            "name": "Tags",
            "value": "Source edit",
            "inline": false
          }
        ],
        "color": 35840
      }
    ]
  },
  {
    "timestamp": 1780871683332,
    "embeds": [
      {
        "title": "Whistle (m +115)",
        "description": "No description provided",
        "author": {
          "name": "Frogt007",
          "url": "https://alter-ego.fandom.com/wiki/Special:Contribs/Frogt007"
        },
        "fields": [
          {
            "name": "Tags",
            "value": "Source edit",
            "inline": false
          }
        ],
        "color": 36352
      }
    ]
  },
  {
    "timestamp": 1780871027067,
    "embeds": [
      {
        "title": "Patient Zero (m -4)",
        "description": "No description provided",
        "author": {
          "name": "Frogt007",
          "url": "https://alter-ego.fandom.com/wiki/Special:Contribs/Frogt007"
        },
        "fields": [
          {
            "name": "Tags",
            "value": "Source edit",
            "inline": false
          }
        ],
        "color": 9175040
      }
    ]
  },
  {
    "timestamp": 1780870959701,
    "embeds": [
      {
        "title": "Husk (m -41)",
        "description": "No description provided",
        "author": {
          "name": "Frogt007",
          "url": "https://alter-ego.fandom.com/wiki/Special:Contribs/Frogt007"
        },
        "fields": [
          {
            "name": "Tags",
            "value": "Manual revert, Source edit",
            "inline": false
          }
        ],
        "color": 9175040
      }
    ]
  },
  {
    "timestamp": 1780870952425,
    "embeds": [
      {
        "title": "Commander (m -29)",
        "description": "No description provided",
        "author": {
          "name": "Frogt007",
          "url": "https://alter-ego.fandom.com/wiki/Special:Contribs/Frogt007"
        },
        "fields": [
          {
            "name": "Tags",
            "value": "Source edit",
            "inline": false
          }
        ],
        "color": 9175040
      }
    ]
  },
  {
    "timestamp": 1780868442663,
    "embeds": [
      {
        "title": "Noob (m -6)",
        "description": "No description provided",
        "author": {
          "name": "Frogt007",
          "url": "https://alter-ego.fandom.com/wiki/Special:Contribs/Frogt007"
        },
        "fields": [
          {
            "name": "Tags",
            "value": "Source edit",
            "inline": false
          }
        ],
        "color": 9175040
      }
    ]
  },
  {
    "timestamp": 1780867210838,
    "embeds": [
      {
        "title": "Caducus ( -120)",
        "description": "Undo revision [46323](<https://alter-ego.fandom.com/wiki/Special:Diff/46323>) by [MisterGuyDudeLol](<https://alter-ego.fandom.com/wiki/Special:Contributions/MisterGuyDudeLol>) \\([talk](<https://alter-ego.fandom.com/wiki/User_talk:MisterGuyDudeLol?action=edit&redlink=1>)\\)",
        "author": {
          "name": "Vwwwiou",
          "url": "https://alter-ego.fandom.com/wiki/Special:Contribs/Vwwwiou"
        },
        "fields": [
          {
            "name": "Tags",
            "value": "Undo",
            "inline": false
          }
        ],
        "color": 9306112
      }
    ]
  },
  {
    "timestamp": 1780867183915,
    "embeds": [
      {
        "title": "Caducus ( -120)",
        "description": "Undo revision [46323](<https://alter-ego.fandom.com/wiki/Special:Diff/46323>) by [MisterGuyDudeLol](<https://alter-ego.fandom.com/wiki/Special:Contributions/MisterGuyDudeLol>) \\([talk](<https://alter-ego.fandom.com/wiki/User_talk:MisterGuyDudeLol?action=edit&redlink=1>)\\)",
        "author": {
          "name": "Vwwwiou",
          "url": "https://alter-ego.fandom.com/wiki/Special:Contribs/Vwwwiou"
        },
        "fields": [
          {
            "name": "Tags",
            "value": "Undo",
            "inline": false
          }
        ],
        "color": 9306112
      }
    ]
  },
  {
    "timestamp": 1780866397414,
    "embeds": [
      {
        "title": "Caducus (m +120)",
        "description": "No description provided",
        "author": {
          "name": "MisterGuyDudeLol",
          "url": "https://alter-ego.fandom.com/wiki/Special:Contribs/MisterGuyDudeLol"
        },
        "fields": [
          {
            "name": "Tags",
            "value": "Mobile web edit, Mobile edit, Visual edit",
            "inline": false
          }
        ],
        "color": 36352
      }
    ]
  },
  {
    "timestamp": 1780865988620,
    "embeds": [
      {
        "title": "Husk (m +41)",
        "description": "No description provided",
        "author": {
          "name": "MisterGuyDudeLol",
          "url": "https://alter-ego.fandom.com/wiki/Special:Contribs/MisterGuyDudeLol"
        },
        "fields": [
          {
            "name": "Tags",
            "value": "Mobile web edit, Mobile edit, Visual edit",
            "inline": false
          }
        ],
        "color": 35840
      }
    ]
  },
  {
    "timestamp": 1780865784938,
    "embeds": [
      {
        "title": "Fjord (m +82)",
        "description": "No description provided",
        "author": {
          "name": "MisterGuyDudeLol",
          "url": "https://alter-ego.fandom.com/wiki/Special:Contribs/MisterGuyDudeLol"
        },
        "fields": [
          {
            "name": "Tags",
            "value": "Mobile web edit, Mobile edit, Visual edit",
            "inline": false
          }
        ],
        "color": 36096
      }
    ]
  },
  {
    "timestamp": 1780865565579,
    "embeds": [
      {
        "title": "Commander (m +9)",
        "description": "No description provided",
        "author": {
          "name": "MisterGuyDudeLol",
          "url": "https://alter-ego.fandom.com/wiki/Special:Contribs/MisterGuyDudeLol"
        },
        "fields": [
          {
            "name": "Tags",
            "value": "Mobile web edit, Mobile edit, Visual edit",
            "inline": false
          }
        ],
        "color": 35840
      }
    ]
  },
  {
    "timestamp": 1780865507361,
    "embeds": [
      {
        "title": "Commander (m +21)",
        "description": "No description provided",
        "author": {
          "name": "MisterGuyDudeLol",
          "url": "https://alter-ego.fandom.com/wiki/Special:Contribs/MisterGuyDudeLol"
        },
        "fields": [
          {
            "name": "Tags",
            "value": "Mobile web edit, Mobile edit, Visual edit",
            "inline": false
          }
        ],
        "color": 35840
      }
    ]
  },
  {
    "timestamp": 1780865370712,
    "embeds": [
      {
        "title": "Patient Zero (m +24)",
        "description": "No description provided",
        "author": {
          "name": "MisterGuyDudeLol",
          "url": "https://alter-ego.fandom.com/wiki/Special:Contribs/MisterGuyDudeLol"
        },
        "fields": [
          {
            "name": "Tags",
            "value": "Mobile web edit, Mobile edit, Visual edit",
            "inline": false
          }
        ],
        "color": 35840
      }
    ]
  },
  {
    "timestamp": 1780865263475,
    "embeds": [
      {
        "title": "Noob (m +14)",
        "description": "No description provided",
        "author": {
          "name": "MisterGuyDudeLol",
          "url": "https://alter-ego.fandom.com/wiki/Special:Contribs/MisterGuyDudeLol"
        },
        "fields": [
          {
            "name": "Tags",
            "value": "Mobile web edit, Mobile edit, Visual edit",
            "inline": false
          }
        ],
        "color": 35840
      }
    ]
  },
  {
    "timestamp": 1780772800396,
    "embeds": [
      {
        "title": "Husk ( -14)",
        "description": "i dont recall them having hps",
        "author": {
          "name": "Gabonnie",
          "url": "https://alter-ego.fandom.com/wiki/Special:Contribs/Gabonnie"
        },
        "fields": [],
        "color": 9175040
      }
    ]
  },
  {
    "timestamp": 1780772792394,
    "embeds": [
      {
        "title": "Caducus ( -15)",
        "description": "\\[IPE-NEXT\\] Quick edit",
        "author": {
          "name": "Gabonnie",
          "url": "https://alter-ego.fandom.com/wiki/Special:Contribs/Gabonnie"
        },
        "fields": [
          {
            "name": "Tags",
            "value": "Manual revert",
            "inline": false
          }
        ],
        "color": 9175040
      }
    ]
  },
  {
    "timestamp": 1780771056730,
    "embeds": [
      {
        "title": "Husk (m +42)",
        "description": "No description provided",
        "author": {
          "name": "Frogt007",
          "url": "https://alter-ego.fandom.com/wiki/Special:Contribs/Frogt007"
        },
        "fields": [
          {
            "name": "Tags",
            "value": "Source edit",
            "inline": false
          }
        ],
        "color": 35840
      }
    ]
  },
  {
    "timestamp": 1780770499166,
    "embeds": [
      {
        "title": "Husk (m +14)",
        "description": "No description provided",
        "author": {
          "name": "Frogt007",
          "url": "https://alter-ego.fandom.com/wiki/Special:Contribs/Frogt007"
        },
        "fields": [
          {
            "name": "Tags",
            "value": "Source edit",
            "inline": false
          }
        ],
        "color": 35840
      }
    ]
  },
  {
    "timestamp": 1780770486628,
    "embeds": [
      {
        "title": "Caducus (m +15)",
        "description": "No description provided",
        "author": {
          "name": "Frogt007",
          "url": "https://alter-ego.fandom.com/wiki/Special:Contribs/Frogt007"
        },
        "fields": [
          {
            "name": "Tags",
            "value": "Source edit",
            "inline": false
          }
        ],
        "color": 35840
      }
    ]
  },
  {
    "timestamp": 1780621937263,
    "embeds": [
      {
        "title": "V0.8.0 ( +10)",
        "description": "\\[IPE-NEXT\\] Quick edit",
        "author": {
          "name": "Gabonnie",
          "url": "https://alter-ego.fandom.com/wiki/Special:Contribs/Gabonnie"
        },
        "fields": [],
        "color": 35840
      }
    ]
  },
  {
    "timestamp": 1780620185181,
    "embeds": [
      {
        "title": "ALTERPEDIA ( +1)",
        "description": "No description provided",
        "author": {
          "name": "Gabonnie",
          "url": "https://alter-ego.fandom.com/wiki/Special:Contribs/Gabonnie"
        },
        "fields": [],
        "color": 35840
      }
    ]
  },
  {
    "timestamp": 1780619431090,
    "embeds": [
      {
        "title": "Uploaded File:DangerSenseAnimated.gif",
        "description": "\\[IPE-NEXT\\] Quick upload",
        "author": {
          "name": "Gabonnie",
          "url": "https://alter-ego.fandom.com/wiki/Special:Contribs/Gabonnie",
          "iconURL": "https://i.imgur.com/egJpa81.png",
          "proxyIconURL": "https://images-ext-1.discordapp.net/external/bcm6sjmxlURnXbAXypCIiySw7h11tU-KcCJ4KDgf8mE/https/i.imgur.com/egJpa81.png"
        },
        "fields": [],
        "color": 12390624
      }
    ]
  },
  {
    "timestamp": 1780619406864,
    "embeds": [
      {
        "title": "Fjord ( +14)",
        "description": "\\[IPE-NEXT\\] Quick edit",
        "author": {
          "name": "Gabonnie",
          "url": "https://alter-ego.fandom.com/wiki/Special:Contribs/Gabonnie"
        },
        "fields": [],
        "color": 35840
      }
    ]
  },
  {
    "timestamp": 1780619294757,
    "embeds": [
      {
        "title": "V0.8.10 ( -10)",
        "description": "\\[IPE-NEXT\\] Quick edit",
        "author": {
          "name": "Gabonnie",
          "url": "https://alter-ego.fandom.com/wiki/Special:Contribs/Gabonnie"
        },
        "fields": [],
        "color": 9175040
      }
    ]
  },
  {
    "timestamp": 1780619252823,
    "embeds": [
      {
        "title": "ALTER EGO ( +2)",
        "description": "\\[IPE-NEXT\\] Quick edit",
        "author": {
          "name": "Gabonnie",
          "url": "https://alter-ego.fandom.com/wiki/Special:Contribs/Gabonnie"
        },
        "fields": [],
        "color": 35840
      }
    ]
  },
  {
    "timestamp": 1780619231984,
    "embeds": [
      {
        "title": "ALTER EGO ( -87)",
        "description": "\\[IPE-NEXT\\] Quick edit",
        "author": {
          "name": "Gabonnie",
          "url": "https://alter-ego.fandom.com/wiki/Special:Contribs/Gabonnie"
        },
        "fields": [],
        "color": 9240576
      }
    ]
  },
  {
    "timestamp": 1780604286985,
    "embeds": [
      {
        "title": "ALTER EGO (m +359)",
        "description": "No description provided",
        "author": {
          "name": "Frogt007",
          "url": "https://alter-ego.fandom.com/wiki/Special:Contribs/Frogt007"
        },
        "fields": [
          {
            "name": "Tags",
            "value": "Source edit",
            "inline": false
          }
        ],
        "color": 37376
      }
    ]
  },
  {
    "timestamp": 1780604171719,
    "embeds": [
      {
        "title": "V0.8.10 (m +319)",
        "description": "No description provided",
        "author": {
          "name": "Frogt007",
          "url": "https://alter-ego.fandom.com/wiki/Special:Contribs/Frogt007"
        },
        "fields": [
          {
            "name": "Tags",
            "value": "Source edit",
            "inline": false
          }
        ],
        "color": 37376
      }
    ]
  },
  {
    "timestamp": 1780603963141,
    "embeds": [
      {
        "title": "Uploaded File:AlterEgoWithTDSIcon.png",
        "description": "No description provided",
        "author": {
          "name": "Frogt007",
          "url": "https://alter-ego.fandom.com/wiki/Special:Contribs/Frogt007",
          "iconURL": "https://i.imgur.com/egJpa81.png",
          "proxyIconURL": "https://images-ext-1.discordapp.net/external/bcm6sjmxlURnXbAXypCIiySw7h11tU-KcCJ4KDgf8mE/https/i.imgur.com/egJpa81.png"
        },
        "fields": [
          {
            "name": "Options",
            "value": "([preview](https://static.wikia.nocookie.net/alter-ego/images/4/48/AlterEgoWithTDSIcon.png/revision/latest?cb=20260604201236&rcgcdw=8903019802))",
            "inline": false
          }
        ],
        "color": 12390624
      }
    ]
  },
  {
    "timestamp": 1780603949489,
    "embeds": [
      {
        "title": "Uploaded File:TDSIconCountdownButAE.png",
        "description": "No description provided",
        "author": {
          "name": "Frogt007",
          "url": "https://alter-ego.fandom.com/wiki/Special:Contribs/Frogt007",
          "iconURL": "https://i.imgur.com/egJpa81.png",
          "proxyIconURL": "https://images-ext-1.discordapp.net/external/bcm6sjmxlURnXbAXypCIiySw7h11tU-KcCJ4KDgf8mE/https/i.imgur.com/egJpa81.png"
        },
        "fields": [
          {
            "name": "Options",
            "value": "([preview](https://static.wikia.nocookie.net/alter-ego/images/7/7e/TDSIconCountdownButAE.png/revision/latest?cb=20260604201226&rcgcdw=8903019739))",
            "inline": false
          }
        ],
        "color": 12390624
      }
    ]
  },
  {
    "timestamp": 1780602366828,
    "embeds": [
      {
        "title": "Updates ( +11)",
        "description": "No description provided",
        "author": {
          "name": "Frogt007",
          "url": "https://alter-ego.fandom.com/wiki/Special:Contribs/Frogt007"
        },
        "fields": [
          {
            "name": "Tags",
            "value": "Source edit",
            "inline": false
          }
        ],
        "color": 35840
      }
    ]
  },
  {
    "timestamp": 1780602302129,
    "embeds": [
      {
        "title": "V0.8.10 (m +122)",
        "description": "No description provided",
        "author": {
          "name": "Frogt007",
          "url": "https://alter-ego.fandom.com/wiki/Special:Contribs/Frogt007"
        },
        "fields": [
          {
            "name": "Tags",
            "value": "Source edit",
            "inline": false
          }
        ],
        "color": 36352
      }
    ]
  },
  {
    "timestamp": 1780601952986,
    "embeds": [
      {
        "title": "Uploaded File:AlterEgoIconV0.8.10-2.png",
        "description": "No description provided",
        "author": {
          "name": "Frogt007",
          "url": "https://alter-ego.fandom.com/wiki/Special:Contribs/Frogt007",
          "iconURL": "https://i.imgur.com/egJpa81.png",
          "proxyIconURL": "https://images-ext-1.discordapp.net/external/bcm6sjmxlURnXbAXypCIiySw7h11tU-KcCJ4KDgf8mE/https/i.imgur.com/egJpa81.png"
        },
        "fields": [],
        "color": 12390624
      }
    ]
  },
  {
    "timestamp": 1780584173645,
    "embeds": [
      {
        "title": "Join For A Bite (m +122)",
        "description": "No description provided",
        "author": {
          "name": "Frogt007",
          "url": "https://alter-ego.fandom.com/wiki/Special:Contribs/Frogt007"
        },
        "fields": [
          {
            "name": "Tags",
            "value": "Source edit",
            "inline": false
          }
        ],
        "color": 36352
      }
    ]
  },
  {
    "timestamp": 1780581029265,
    "embeds": [
      {
        "title": "Liar Dance (m 0)",
        "description": "No description provided",
        "author": {
          "name": "Frogt007",
          "url": "https://alter-ego.fandom.com/wiki/Special:Contribs/Frogt007"
        },
        "fields": [
          {
            "name": "Tags",
            "value": "Source edit",
            "inline": false
          }
        ],
        "color": 8750469
      }
    ]
  },
  {
    "timestamp": 1780580872197,
    "embeds": [
      {
        "title": "Liar Dance ( +255)",
        "description": "Added trivia",
        "author": {
          "name": "Frogt007",
          "url": "https://alter-ego.fandom.com/wiki/Special:Contribs/Frogt007"
        },
        "fields": [
          {
            "name": "Tags",
            "value": "Source edit",
            "inline": false
          }
        ],
        "color": 36864
      }
    ]
  },
  {
    "timestamp": 1780578705609,
    "embeds": [
      {
        "title": "Pocoyo (m -2)",
        "description": "No description provided",
        "author": {
          "name": "Frogt007",
          "url": "https://alter-ego.fandom.com/wiki/Special:Contribs/Frogt007"
        },
        "fields": [
          {
            "name": "Tags",
            "value": "Source edit",
            "inline": false
          }
        ],
        "color": 9175040
      }
    ]
  },
  {
    "timestamp": 1780578653077,
    "embeds": [
      {
        "title": "Pocoyo ( +469)",
        "description": "No description provided",
        "author": {
          "name": "Frogt007",
          "url": "https://alter-ego.fandom.com/wiki/Special:Contribs/Frogt007"
        },
        "fields": [
          {
            "name": "Tags",
            "value": "Source edit",
            "inline": false
          }
        ],
        "color": 38144
      }
    ]
  },
  {
    "timestamp": 1780577038097,
    "embeds": [
      {
        "title": "Tokyo Dance (m +199)",
        "description": "No description provided",
        "author": {
          "name": "Frogt007",
          "url": "https://alter-ego.fandom.com/wiki/Special:Contribs/Frogt007"
        },
        "fields": [
          {
            "name": "Tags",
            "value": "Source edit",
            "inline": false
          }
        ],
        "color": 36608
      }
    ]
  },
  {
    "timestamp": 1780576128172,
    "embeds": [
      {
        "title": "With Friends (m +1)",
        "description": "No description provided",
        "author": {
          "name": "Frogt007",
          "url": "https://alter-ego.fandom.com/wiki/Special:Contribs/Frogt007"
        },
        "fields": [
          {
            "name": "Tags",
            "value": "Source edit",
            "inline": false
          }
        ],
        "color": 35840
      }
    ]
  },
  {
    "timestamp": 1780576092776,
    "embeds": [
      {
        "title": "Cry For Me (m +22)",
        "description": "No description provided",
        "author": {
          "name": "Frogt007",
          "url": "https://alter-ego.fandom.com/wiki/Special:Contribs/Frogt007"
        },
        "fields": [
          {
            "name": "Tags",
            "value": "Source edit",
            "inline": false
          }
        ],
        "color": 35840
      }
    ]
  },
  {
    "timestamp": 1780566173267,
    "embeds": [
      {
        "title": "Island Asylum (m +7)",
        "description": "[→Trivia](<https://alter-ego.fandom.com/wiki/Island_Asylum#Trivia>)",
        "author": {
          "name": "Vwwwiou1",
          "url": "https://alter-ego.fandom.com/wiki/Special:Contribs/Vwwwiou1"
        },
        "fields": [],
        "color": 35840
      }
    ]
  },
  {
    "timestamp": 1780544031178,
    "embeds": [
      {
        "title": "MediaWiki:ThankYou.js ( +2)",
        "description": "\\[IPE-NEXT\\] Quick edit",
        "author": {
          "name": "Gabonnie",
          "url": "https://alter-ego.fandom.com/wiki/Special:Contribs/Gabonnie"
        },
        "fields": [],
        "color": 35840
      }
    ]
  },
  {
    "timestamp": 1780543879611,
    "embeds": [
      {
        "title": "MediaWiki:ThankYou.js ( 0)",
        "description": "\\[IPE-NEXT\\] Quick edit",
        "author": {
          "name": "Gabonnie",
          "url": "https://alter-ego.fandom.com/wiki/Special:Contribs/Gabonnie"
        },
        "fields": [],
        "color": 8750469
      }
    ]
  },
  {
    "timestamp": 1780540384251,
    "embeds": [
      {
        "title": "Template:Alter ( +4)",
        "description": "\\[IPE-NEXT\\] Quick edit",
        "author": {
          "name": "Gabonnie",
          "url": "https://alter-ego.fandom.com/wiki/Special:Contribs/Gabonnie"
        },
        "fields": [],
        "color": 35840
      }
    ]
  },
  {
    "timestamp": 1780540365089,
    "embeds": [
      {
        "title": "Template:Victim ( +4)",
        "description": "\\[IPE-NEXT\\] Quick edit",
        "author": {
          "name": "Gabonnie",
          "url": "https://alter-ego.fandom.com/wiki/Special:Contribs/Gabonnie"
        },
        "fields": [],
        "color": 35840
      }
    ]
  },
  {
    "timestamp": 1780540057667,
    "embeds": [
      {
        "title": "Template:Alter ( +12)",
        "description": "\\[IPE-NEXT\\] Quick edit",
        "author": {
          "name": "Gabonnie",
          "url": "https://alter-ego.fandom.com/wiki/Special:Contribs/Gabonnie"
        },
        "fields": [],
        "color": 35840
      }
    ]
  },
  {
    "timestamp": 1780540031586,
    "embeds": [
      {
        "title": "Template:Victim/styles.css ( +40)",
        "description": "\\[IPE-NEXT\\] Quick edit",
        "author": {
          "name": "Gabonnie",
          "url": "https://alter-ego.fandom.com/wiki/Special:Contribs/Gabonnie"
        },
        "fields": [],
        "color": 35840
      }
    ]
  },
  {
    "timestamp": 1780540000881,
    "embeds": [
      {
        "title": "Template:Alter ( -7)",
        "description": "\\[IPE-NEXT\\] Quick edit",
        "author": {
          "name": "Gabonnie",
          "url": "https://alter-ego.fandom.com/wiki/Special:Contribs/Gabonnie"
        },
        "fields": [],
        "color": 9175040
      }
    ]
  },
  {
    "timestamp": 1780539920770,
    "embeds": [
      {
        "title": "Template:Alter ( -4)",
        "description": "\\[IPE-NEXT\\] Quick edit",
        "author": {
          "name": "Gabonnie",
          "url": "https://alter-ego.fandom.com/wiki/Special:Contribs/Gabonnie"
        },
        "fields": [],
        "color": 9175040
      }
    ]
  },
  {
    "timestamp": 1780539890189,
    "embeds": [
      {
        "title": "Template:Alter ( +213)",
        "description": "No description provided",
        "author": {
          "name": "Gabonnie",
          "url": "https://alter-ego.fandom.com/wiki/Special:Contribs/Gabonnie"
        },
        "fields": [],
        "color": 36864
      }
    ]
  },
  {
    "timestamp": 1780539646917,
    "embeds": [
      {
        "title": "Template:Victim ( +126)",
        "description": "No description provided",
        "author": {
          "name": "Gabonnie",
          "url": "https://alter-ego.fandom.com/wiki/Special:Contribs/Gabonnie"
        },
        "fields": [],
        "color": 36352
      }
    ]
  },
  {
    "timestamp": 1780539590837,
    "embeds": [
      {
        "title": "Template:Map ( +138)",
        "description": "No description provided",
        "author": {
          "name": "Gabonnie",
          "url": "https://alter-ego.fandom.com/wiki/Special:Contribs/Gabonnie"
        },
        "fields": [],
        "color": 36352
      }
    ]
  },
  {
    "timestamp": 1780539347761,
    "embeds": [
      {
        "title": "Template:Victim ( +6)",
        "description": "\\[IPE-NEXT\\] Quick edit",
        "author": {
          "name": "Gabonnie",
          "url": "https://alter-ego.fandom.com/wiki/Special:Contribs/Gabonnie"
        },
        "fields": [],
        "color": 35840
      }
    ]
  },
  {
    "timestamp": 1780539256081,
    "embeds": [
      {
        "title": "Template:Victim/styles.css ((N!)  +50)",
        "description": "Created page with \"\\[data-source=\"health\"\\] .pi-data-value \\{ flex\\: 1; \\}\"",
        "author": {
          "name": "Gabonnie",
          "url": "https://alter-ego.fandom.com/wiki/Special:Contribs/Gabonnie",
          "iconURL": "https://i.imgur.com/6HIbEq8.png",
          "proxyIconURL": "https://images-ext-1.discordapp.net/external/VS_4fQ2eCViOTUnSfHsnOXeqwafKOO54j1aZT2Ka-b8/https/i.imgur.com/6HIbEq8.png"
        },
        "fields": [],
        "color": 35840
      }
    ]
  },
  {
    "timestamp": 1780539235237,
    "embeds": [
      {
        "title": "Template:Victim ( +50)",
        "description": "\\[IPE-NEXT\\] Quick edit",
        "author": {
          "name": "Gabonnie",
          "url": "https://alter-ego.fandom.com/wiki/Special:Contribs/Gabonnie"
        },
        "fields": [],
        "color": 35840
      }
    ]
  },
  {
    "timestamp": 1780539227959,
    "embeds": [
      {
        "title": "Template:Map ( -1)",
        "description": "\\[IPE-NEXT\\] Quick edit",
        "author": {
          "name": "Gabonnie",
          "url": "https://alter-ego.fandom.com/wiki/Special:Contribs/Gabonnie"
        },
        "fields": [],
        "color": 9175040
      }
    ]
  },
  {
    "timestamp": 1780539148326,
    "embeds": [
      {
        "title": "Template:Victim ( +72)",
        "description": "No description provided",
        "author": {
          "name": "Gabonnie",
          "url": "https://alter-ego.fandom.com/wiki/Special:Contribs/Gabonnie"
        },
        "fields": [],
        "color": 36096
      }
    ]
  },
  {
    "timestamp": 1780538914012,
    "embeds": [
      {
        "title": "Template:Victim ( -12)",
        "description": "\\[IPE-NEXT\\] Quick edit",
        "author": {
          "name": "Gabonnie",
          "url": "https://alter-ego.fandom.com/wiki/Special:Contribs/Gabonnie"
        },
        "fields": [],
        "color": 9175040
      }
    ]
  },
  {
    "timestamp": 1780538740558,
    "embeds": [
      {
        "title": "Template:Victim ( -6)",
        "description": "No description provided",
        "author": {
          "name": "Gabonnie",
          "url": "https://alter-ego.fandom.com/wiki/Special:Contribs/Gabonnie"
        },
        "fields": [],
        "color": 9175040
      }
    ]
  },
  {
    "timestamp": 1780526804565,
    "embeds": [
      {
        "title": "Crossroads ( +20)",
        "description": "No description provided",
        "author": {
          "name": "Gabonnie",
          "url": "https://alter-ego.fandom.com/wiki/Special:Contribs/Gabonnie"
        },
        "fields": [
          {
            "name": "Tags",
            "value": "Advanced mobile edit, Mobile web edit, Mobile edit, Source edit",
            "inline": false
          }
        ],
        "color": 35840
      }
    ]
  },
  {
    "timestamp": 1780526493721,
    "embeds": [
      {
        "title": "Crossroads ( -1)",
        "description": "No description provided",
        "author": {
          "name": "Frogt007",
          "url": "https://alter-ego.fandom.com/wiki/Special:Contribs/Frogt007"
        },
        "fields": [
          {
            "name": "Tags",
            "value": "Source edit",
            "inline": false
          }
        ],
        "color": 9175040
      }
    ]
  },
  {
    "timestamp": 1780526462510,
    "embeds": [
      {
        "title": "Crossroads (m +91)",
        "description": "No description provided",
        "author": {
          "name": "Frogt007",
          "url": "https://alter-ego.fandom.com/wiki/Special:Contribs/Frogt007"
        },
        "fields": [
          {
            "name": "Tags",
            "value": "Source edit",
            "inline": false
          }
        ],
        "color": 36096
      }
    ]
  },
  {
    "timestamp": 1780521241655,
    "embeds": [
      {
        "title": "Crossroads (m 0)",
        "description": "No description provided",
        "author": {
          "name": "Frogt007",
          "url": "https://alter-ego.fandom.com/wiki/Special:Contribs/Frogt007"
        },
        "fields": [
          {
            "name": "Tags",
            "value": "Source edit",
            "inline": false
          }
        ],
        "color": 8750469
      }
    ]
  },
  {
    "timestamp": 1780521198297,
    "embeds": [
      {
        "title": "Map:Crossroads ( +1058)",
        "description": "Added few locations of consumables",
        "author": {
          "name": "Frogt007",
          "url": "https://alter-ego.fandom.com/wiki/Special:Contribs/Frogt007"
        },
        "fields": [],
        "color": 40960
      }
    ]
  },
  {
    "timestamp": 1780521142662,
    "embeds": [
      {
        "title": "Uploaded File:CrossroadsV0.7.3-ConsumLoc6.jpg",
        "description": "No description provided",
        "author": {
          "name": "Frogt007",
          "url": "https://alter-ego.fandom.com/wiki/Special:Contribs/Frogt007",
          "iconURL": "https://i.imgur.com/egJpa81.png",
          "proxyIconURL": "https://images-ext-1.discordapp.net/external/bcm6sjmxlURnXbAXypCIiySw7h11tU-KcCJ4KDgf8mE/https/i.imgur.com/egJpa81.png"
        },
        "fields": [
          {
            "name": "Options",
            "value": "([preview](https://static.wikia.nocookie.net/alter-ego/images/2/22/CrossroadsV0.7.3-ConsumLoc6.jpg/revision/latest?cb=20260603211211&rcgcdw=8902605679))",
            "inline": false
          }
        ],
        "color": 12390624
      }
    ]
  },
  {
    "timestamp": 1780521087849,
    "embeds": [
      {
        "title": "Uploaded File:CrossroadsV0.7.3-ConsumLoc5.jpg",
        "description": "No description provided",
        "author": {
          "name": "Frogt007",
          "url": "https://alter-ego.fandom.com/wiki/Special:Contribs/Frogt007",
          "iconURL": "https://i.imgur.com/egJpa81.png",
          "proxyIconURL": "https://images-ext-1.discordapp.net/external/bcm6sjmxlURnXbAXypCIiySw7h11tU-KcCJ4KDgf8mE/https/i.imgur.com/egJpa81.png"
        },
        "fields": [
          {
            "name": "Options",
            "value": "([preview](https://static.wikia.nocookie.net/alter-ego/images/c/c2/CrossroadsV0.7.3-ConsumLoc5.jpg/revision/latest?cb=20260603211119&rcgcdw=8902605431))",
            "inline": false
          }
        ],
        "color": 12390624
      }
    ]
  },
  {
    "timestamp": 1780515217160,
    "embeds": [
      {
        "title": "ALTERPEDIA ( +2)",
        "description": "\\[IPE-NEXT\\] Quick edit",
        "author": {
          "name": "Gabonnie",
          "url": "https://alter-ego.fandom.com/wiki/Special:Contribs/Gabonnie"
        },
        "fields": [],
        "color": 35840
      }
    ]
  },
  {
    "timestamp": 1780478458398,
    "embeds": [
      {
        "title": "MediaWiki:Gadget-FloatingContainer.css ( 0)",
        "description": "\\[IPE-NEXT\\] Quick edit",
        "author": {
          "name": "Gabonnie",
          "url": "https://alter-ego.fandom.com/wiki/Special:Contribs/Gabonnie"
        },
        "fields": [],
        "color": 8750469
      }
    ]
  },
  {
    "timestamp": 1780475234589,
    "embeds": [
      {
        "title": "MediaWiki:ThankYou.css ( +46)",
        "description": "\\[IPE-NEXT\\] Quick edit",
        "author": {
          "name": "Gabonnie",
          "url": "https://alter-ego.fandom.com/wiki/Special:Contribs/Gabonnie"
        },
        "fields": [],
        "color": 35840
      }
    ]
  },
  {
    "timestamp": 1780475159156,
    "embeds": [
      {
        "title": "MediaWiki:ThankYou.js ( +27)",
        "description": "\\[IPE-NEXT\\] Quick edit",
        "author": {
          "name": "Gabonnie",
          "url": "https://alter-ego.fandom.com/wiki/Special:Contribs/Gabonnie"
        },
        "fields": [],
        "color": 35840
      }
    ]
  },
  {
    "timestamp": 1780437275501,
    "embeds": [
      {
        "title": "Maps (m +1)",
        "description": "Changed \"Removed\" to \"Upcoming\" cuz crossroads is going to return with rework",
        "author": {
          "name": "Frogt007",
          "url": "https://alter-ego.fandom.com/wiki/Special:Contribs/Frogt007"
        },
        "fields": [
          {
            "name": "Tags",
            "value": "Manual revert, Source edit",
            "inline": false
          }
        ],
        "color": 35840
      }
    ]
  },
  {
    "timestamp": 1780437227584,
    "embeds": [
      {
        "title": "Template:MapNav (m +862)",
        "description": "added office and moved crossroads to upcoming tab",
        "author": {
          "name": "Frogt007",
          "url": "https://alter-ego.fandom.com/wiki/Special:Contribs/Frogt007"
        },
        "fields": [
          {
            "name": "Tags",
            "value": "Source edit",
            "inline": false
          }
        ],
        "color": 39936
      }
    ]
  },
  {
    "timestamp": 1780419682618,
    "embeds": [
      {
        "title": "Map:Crossroads ( +534)",
        "description": "No description provided",
        "author": {
          "name": "Frogt007",
          "url": "https://alter-ego.fandom.com/wiki/Special:Contribs/Frogt007"
        },
        "fields": [],
        "color": 38400
      }
    ]
  },
  {
    "timestamp": 1780419419377,
    "embeds": [
      {
        "title": "Uploaded File:CrossroadsV0.7.2-ConsumLoc5.png.png",
        "description": "No description provided",
        "author": {
          "name": "Frogt007",
          "url": "https://alter-ego.fandom.com/wiki/Special:Contribs/Frogt007",
          "iconURL": "https://i.imgur.com/egJpa81.png",
          "proxyIconURL": "https://images-ext-1.discordapp.net/external/bcm6sjmxlURnXbAXypCIiySw7h11tU-KcCJ4KDgf8mE/https/i.imgur.com/egJpa81.png"
        },
        "fields": [],
        "color": 12390624
      }
    ]
  },
  {
    "timestamp": 1780352532404,
    "embeds": [
      {
        "title": "V0.8.10 (m +3)",
        "description": "No description provided",
        "author": {
          "name": "Frogt007",
          "url": "https://alter-ego.fandom.com/wiki/Special:Contribs/Frogt007"
        },
        "fields": [
          {
            "name": "Tags",
            "value": "Source edit",
            "inline": false
          }
        ],
        "color": 35840
      }
    ]
  },
  {
    "timestamp": 1780352472022,
    "embeds": [
      {
        "title": "Downed But Not Out (m +179)",
        "description": "No description provided",
        "author": {
          "name": "Frogt007",
          "url": "https://alter-ego.fandom.com/wiki/Special:Contribs/Frogt007"
        },
        "fields": [
          {
            "name": "Tags",
            "value": "Source edit",
            "inline": false
          }
        ],
        "color": 36608
      }
    ]
  },
  {
    "timestamp": 1780352232247,
    "embeds": [
      {
        "title": "V0.8.10 (m +69)",
        "description": "No description provided",
        "author": {
          "name": "Frogt007",
          "url": "https://alter-ego.fandom.com/wiki/Special:Contribs/Frogt007"
        },
        "fields": [
          {
            "name": "Tags",
            "value": "Source edit",
            "inline": false
          }
        ],
        "color": 36096
      }
    ]
  },
  {
    "timestamp": 1780352190480,
    "embeds": [
      {
        "title": "Uploaded File:CoolGreenReviveUI.png",
        "description": "No description provided",
        "author": {
          "name": "Frogt007",
          "url": "https://alter-ego.fandom.com/wiki/Special:Contribs/Frogt007",
          "iconURL": "https://i.imgur.com/egJpa81.png",
          "proxyIconURL": "https://images-ext-1.discordapp.net/external/bcm6sjmxlURnXbAXypCIiySw7h11tU-KcCJ4KDgf8mE/https/i.imgur.com/egJpa81.png"
        },
        "fields": [
          {
            "name": "Options",
            "value": "([preview](https://static.wikia.nocookie.net/alter-ego/images/4/47/CoolGreenReviveUI.png/revision/latest?cb=20260601221628&rcgcdw=8901760946))",
            "inline": false
          }
        ],
        "color": 12390624
      }
    ]
  },
  {
    "timestamp": 1780352062728,
    "embeds": [
      {
        "title": "V0.8.10 (m +50)",
        "description": "No description provided",
        "author": {
          "name": "Frogt007",
          "url": "https://alter-ego.fandom.com/wiki/Special:Contribs/Frogt007"
        },
        "fields": [
          {
            "name": "Tags",
            "value": "Source edit",
            "inline": false
          }
        ],
        "color": 35840
      }
    ]
  },
  {
    "timestamp": 1780351842272,
    "embeds": [
      {
        "title": "Crossroads (m +3)",
        "description": "No description provided",
        "author": {
          "name": "Frogt007",
          "url": "https://alter-ego.fandom.com/wiki/Special:Contribs/Frogt007"
        },
        "fields": [
          {
            "name": "Tags",
            "value": "Source edit",
            "inline": false
          }
        ],
        "color": 35840
      }
    ]
  },
  {
    "timestamp": 1780351808169,
    "embeds": [
      {
        "title": "Map:Crossroads ( +2889)",
        "description": "added some consumables locs, from what i could find",
        "author": {
          "name": "Frogt007",
          "url": "https://alter-ego.fandom.com/wiki/Special:Contribs/Frogt007"
        },
        "fields": [],
        "color": 49920
      }
    ]
  },
  {
    "timestamp": 1780351227454,
    "embeds": [
      {
        "title": "Uploaded File:CrossroadsV0.7.0-ConsumLoc.png",
        "description": "from v0.7.0  screenshot by me",
        "author": {
          "name": "Frogt007",
          "url": "https://alter-ego.fandom.com/wiki/Special:Contribs/Frogt007",
          "iconURL": "https://i.imgur.com/egJpa81.png",
          "proxyIconURL": "https://images-ext-1.discordapp.net/external/bcm6sjmxlURnXbAXypCIiySw7h11tU-KcCJ4KDgf8mE/https/i.imgur.com/egJpa81.png"
        },
        "fields": [],
        "color": 12390624
      }
    ]
  },
  {
    "timestamp": 1780350617203,
    "embeds": [
      {
        "title": "Uploaded File:CrossroadsV0.7.2-ConsumLoc4.png",
        "description": "No description provided",
        "author": {
          "name": "Frogt007",
          "url": "https://alter-ego.fandom.com/wiki/Special:Contribs/Frogt007",
          "iconURL": "https://i.imgur.com/egJpa81.png",
          "proxyIconURL": "https://images-ext-1.discordapp.net/external/bcm6sjmxlURnXbAXypCIiySw7h11tU-KcCJ4KDgf8mE/https/i.imgur.com/egJpa81.png"
        },
        "fields": [
          {
            "name": "Options",
            "value": "([preview](https://static.wikia.nocookie.net/alter-ego/images/6/6d/CrossroadsV0.7.2-ConsumLoc4.png/revision/latest?cb=20260601215012&rcgcdw=8901753066))",
            "inline": false
          }
        ],
        "color": 12390624
      }
    ]
  },
  {
    "timestamp": 1780349905241,
    "embeds": [
      {
        "title": "Moved ⤷ File:CrossroadsV0.7.2-ConsumLoc3.png to File:CrossroadsV0.7.6-ConsumLoc.png",
        "description": "A redirect has been made. No description provided",
        "author": {
          "name": "Frogt007",
          "url": "https://alter-ego.fandom.com/wiki/Special:Contribs/Frogt007",
          "iconURL": "https://i.imgur.com/eXz9dog.png",
          "proxyIconURL": "https://images-ext-1.discordapp.net/external/JQ9HTtN3PLy5aDN_2sJ9wQSMnRpmWNKbHMZnJ4iPKbM/https/i.imgur.com/eXz9dog.png"
        },
        "fields": [],
        "color": 25600
      }
    ]
  },
  {
    "timestamp": 1780349758340,
    "embeds": [
      {
        "title": "Uploaded File:CrossroadsV0.7.2-ConsumLoc3.png",
        "description": "No description provided",
        "author": {
          "name": "Frogt007",
          "url": "https://alter-ego.fandom.com/wiki/Special:Contribs/Frogt007",
          "iconURL": "https://i.imgur.com/egJpa81.png",
          "proxyIconURL": "https://images-ext-1.discordapp.net/external/bcm6sjmxlURnXbAXypCIiySw7h11tU-KcCJ4KDgf8mE/https/i.imgur.com/egJpa81.png"
        },
        "fields": [],
        "color": 12390624
      }
    ]
  },
  {
    "timestamp": 1780346193274,
    "embeds": [
      {
        "title": "Uploaded File:CrossroadsV0.7.2-ConsumLoc2.png.png",
        "description": "No description provided",
        "author": {
          "name": "Frogt007",
          "url": "https://alter-ego.fandom.com/wiki/Special:Contribs/Frogt007",
          "iconURL": "https://i.imgur.com/egJpa81.png",
          "proxyIconURL": "https://images-ext-1.discordapp.net/external/bcm6sjmxlURnXbAXypCIiySw7h11tU-KcCJ4KDgf8mE/https/i.imgur.com/egJpa81.png"
        },
        "fields": [
          {
            "name": "Options",
            "value": "([preview](https://static.wikia.nocookie.net/alter-ego/images/f/fb/CrossroadsV0.7.2-ConsumLoc2.png.png/revision/latest?cb=20260601203630&rcgcdw=8901730958))",
            "inline": false
          }
        ],
        "color": 12390624
      }
    ]
  },
  {
    "timestamp": 1780345547887,
    "embeds": [
      {
        "title": "Uploaded File:CrossroadsV0.7.2-ConsumLoc.png.png",
        "description": "No description provided",
        "author": {
          "name": "Frogt007",
          "url": "https://alter-ego.fandom.com/wiki/Special:Contribs/Frogt007",
          "iconURL": "https://i.imgur.com/egJpa81.png",
          "proxyIconURL": "https://images-ext-1.discordapp.net/external/bcm6sjmxlURnXbAXypCIiySw7h11tU-KcCJ4KDgf8mE/https/i.imgur.com/egJpa81.png"
        },
        "fields": [],
        "color": 12390624
      }
    ]
  },
  {
    "timestamp": 1780329117265,
    "embeds": [
      {
        "title": "B-Man ( +40)",
        "description": "No description provided",
        "author": {
          "name": "RustyChroma",
          "url": "https://alter-ego.fandom.com/wiki/Special:Contribs/RustyChroma"
        },
        "fields": [],
        "color": 35840
      }
    ]
  },
  {
    "timestamp": 1780325625759,
    "embeds": [
      {
        "title": "Alter Egos ( +1368)",
        "description": "No description provided",
        "author": {
          "name": "Gabonnie",
          "url": "https://alter-ego.fandom.com/wiki/Special:Contribs/Gabonnie"
        },
        "fields": [],
        "color": 42496
      }
    ]
  },
  {
    "timestamp": 1780324767390,
    "embeds": [
      {
        "title": "Patient Zero ( +77)",
        "description": "\\[IPE-NEXT\\] Quick edit",
        "author": {
          "name": "Gabonnie",
          "url": "https://alter-ego.fandom.com/wiki/Special:Contribs/Gabonnie"
        },
        "fields": [],
        "color": 36096
      }
    ]
  },
  {
    "timestamp": 1780323998014,
    "embeds": [
      {
        "title": "Template:MechanicNav (m +49)",
        "description": "No description provided",
        "author": {
          "name": "Frogt007",
          "url": "https://alter-ego.fandom.com/wiki/Special:Contribs/Frogt007"
        },
        "fields": [
          {
            "name": "Tags",
            "value": "Source edit",
            "inline": false
          }
        ],
        "color": 35840
      }
    ]
  },
  {
    "timestamp": 1780323374394,
    "embeds": [
      {
        "title": "Labyrinth ( -1)",
        "description": "\\[IPE-NEXT\\] Quick edit",
        "author": {
          "name": "Gabonnie",
          "url": "https://alter-ego.fandom.com/wiki/Special:Contribs/Gabonnie"
        },
        "fields": [],
        "color": 9175040
      }
    ]
  },
  {
    "timestamp": 1780323254389,
    "embeds": [
      {
        "title": "Labyrinth ( +24)",
        "description": "\\[IPE-NEXT\\] Quick edit",
        "author": {
          "name": "Gabonnie",
          "url": "https://alter-ego.fandom.com/wiki/Special:Contribs/Gabonnie"
        },
        "fields": [],
        "color": 35840
      }
    ]
  },
  {
    "timestamp": 1780323194860,
    "embeds": [
      {
        "title": "Labyrinth ( +681)",
        "description": "\\[IPE-NEXT\\] Quick edit",
        "author": {
          "name": "Gabonnie",
          "url": "https://alter-ego.fandom.com/wiki/Special:Contribs/Gabonnie"
        },
        "fields": [],
        "color": 39168
      }
    ]
  },
  {
    "timestamp": 1780322756899,
    "embeds": [
      {
        "title": "Labyrinth ( +1744)",
        "description": "No description provided",
        "author": {
          "name": "Gabonnie",
          "url": "https://alter-ego.fandom.com/wiki/Special:Contribs/Gabonnie"
        },
        "fields": [],
        "color": 44288
      }
    ]
  },
  {
    "timestamp": 1780322534809,
    "embeds": [
      {
        "title": "User:JustNumberFive ((N!)  +45)",
        "description": "Created page with \"what are you doing here i dont play alter ego\"",
        "author": {
          "name": "JustNumberFive",
          "url": "https://alter-ego.fandom.com/wiki/Special:Contribs/JustNumberFive",
          "iconURL": "https://i.imgur.com/6HIbEq8.png",
          "proxyIconURL": "https://images-ext-1.discordapp.net/external/VS_4fQ2eCViOTUnSfHsnOXeqwafKOO54j1aZT2Ka-b8/https/i.imgur.com/6HIbEq8.png"
        },
        "fields": [
          {
            "name": "Tags",
            "value": "Visual edit",
            "inline": false
          }
        ],
        "color": 35840
      }
    ]
  },
  {
    "timestamp": 1780321735002,
    "embeds": [
      {
        "title": "Template:Speculation ( -43)",
        "description": "\\[IPE-NEXT\\] Quick edit",
        "author": {
          "name": "Gabonnie",
          "url": "https://alter-ego.fandom.com/wiki/Special:Contribs/Gabonnie"
        },
        "fields": [],
        "color": 9175040
      }
    ]
  },
  {
    "timestamp": 1780321489965,
    "embeds": [
      {
        "title": "Template:Speculation ((N!)  +337)",
        "description": "Created page with \"\\<div class=\"d-flex align-items-center gap-3 mb-3 w-100 p-2 bg-splatter-red text-white border-border border-2\"\\>[48px](<https://alter-ego.fandom.com/wiki/File:LucienTired.png>)\\<div\\>'''Speculation'''\\<br\\/\\>''This section works with assumptions that have not been outright confirmed.\\<\\/div\\>\\<\\/div\\>\\{\\{#ifeq\\:\\{\\{NAMESPACE\\}\\}\\|\\|[Category\\:Stubs](<https://alter-ego.fandom.com/wiki/Category:Stubs>)\\}\\}\\<noinclude\\>\\{\\{Documentation\\}\\}\\<\\/noinclude\\>\"",
        "author": {
          "name": "Gabonnie",
          "url": "https://alter-ego.fandom.com/wiki/Special:Contribs/Gabonnie",
          "iconURL": "https://i.imgur.com/6HIbEq8.png",
          "proxyIconURL": "https://images-ext-1.discordapp.net/external/VS_4fQ2eCViOTUnSfHsnOXeqwafKOO54j1aZT2Ka-b8/https/i.imgur.com/6HIbEq8.png"
        },
        "fields": [],
        "color": 37376
      }
    ]
  },
  {
    "timestamp": 1780321453577,
    "embeds": [
      {
        "title": "Uploaded File:LucienTIred.png",
        "description": "\\[IPE-NEXT\\] Quick upload",
        "author": {
          "name": "Gabonnie",
          "url": "https://alter-ego.fandom.com/wiki/Special:Contribs/Gabonnie",
          "iconURL": "https://i.imgur.com/egJpa81.png",
          "proxyIconURL": "https://images-ext-1.discordapp.net/external/bcm6sjmxlURnXbAXypCIiySw7h11tU-KcCJ4KDgf8mE/https/i.imgur.com/egJpa81.png"
        },
        "fields": [
          {
            "name": "Options",
            "value": "([preview](https://static.wikia.nocookie.net/alter-ego/images/b/b6/LucienTIred.png/revision/latest?cb=20260601134405&rcgcdw=8901607243))",
            "inline": false
          }
        ],
        "color": 12390624
      }
    ]
  },
  {
    "timestamp": 1780319749286,
    "embeds": [
      {
        "title": "Chirp ( 0)",
        "description": "\\[IPE-NEXT\\] Quick edit",
        "author": {
          "name": "Gabonnie",
          "url": "https://alter-ego.fandom.com/wiki/Special:Contribs/Gabonnie"
        },
        "fields": [],
        "color": 8750469
      }
    ]
  },
  {
    "timestamp": 1780319446847,
    "embeds": [
      {
        "title": "Follower ( -22)",
        "description": "\\[IPE-NEXT\\] Quick edit",
        "author": {
          "name": "Gabonnie",
          "url": "https://alter-ego.fandom.com/wiki/Special:Contribs/Gabonnie"
        },
        "fields": [],
        "color": 9175040
      }
    ]
  },
  {
    "timestamp": 1780286369200,
    "embeds": [
      {
        "title": "Follower ( -23)",
        "description": "\\[IPE-NEXT\\] Quick edit",
        "author": {
          "name": "Gabonnie",
          "url": "https://alter-ego.fandom.com/wiki/Special:Contribs/Gabonnie"
        },
        "fields": [],
        "color": 9175040
      }
    ]
  },
  {
    "timestamp": 1780286341302,
    "embeds": [
      {
        "title": "Deleted page File:EllieCite.png",
        "description": "\\[IPE-NEXT\\] Quick delete",
        "author": {
          "name": "Gabonnie",
          "url": "https://alter-ego.fandom.com/wiki/Special:Contribs/Gabonnie",
          "iconURL": "https://i.imgur.com/BU77GD3.png",
          "proxyIconURL": "https://images-ext-1.discordapp.net/external/o4v4Gdxz1FXMQTjdhfbvad8yBFHCyNbgZSUWLi5Z6RY/https/i.imgur.com/BU77GD3.png"
        },
        "fields": [],
        "color": 1
      }
    ]
  },
  {
    "timestamp": 1780282604317,
    "embeds": [
      {
        "title": "Follower ( +5)",
        "description": "[→Trivia](<https://alter-ego.fandom.com/wiki/Follower#Trivia>)",
        "author": {
          "name": "RustyChroma",
          "url": "https://alter-ego.fandom.com/wiki/Special:Contribs/RustyChroma"
        },
        "fields": [],
        "color": 35840
      }
    ]
  },
  {
    "timestamp": 1780282463166,
    "embeds": [
      {
        "title": "Follower ( +24)",
        "description": "[→Trivia](<https://alter-ego.fandom.com/wiki/Follower#Trivia>)",
        "author": {
          "name": "RustyChroma",
          "url": "https://alter-ego.fandom.com/wiki/Special:Contribs/RustyChroma"
        },
        "fields": [],
        "color": 35840
      }
    ]
  },
  {
    "timestamp": 1780282400082,
    "embeds": [
      {
        "title": "Uploaded File:EllieCite.png",
        "description": "\\[IPE-NEXT\\] Quick upload",
        "author": {
          "name": "RustyChroma",
          "url": "https://alter-ego.fandom.com/wiki/Special:Contribs/RustyChroma",
          "iconURL": "https://i.imgur.com/egJpa81.png",
          "proxyIconURL": "https://images-ext-1.discordapp.net/external/bcm6sjmxlURnXbAXypCIiySw7h11tU-KcCJ4KDgf8mE/https/i.imgur.com/egJpa81.png"
        },
        "fields": [],
        "color": 12390624
      }
    ]
  },
  {
    "timestamp": 1780282288607,
    "embeds": [
      {
        "title": "Follower ( -107)",
        "description": "[→Relationships](<https://alter-ego.fandom.com/wiki/Follower#Relationships>)",
        "author": {
          "name": "RustyChroma",
          "url": "https://alter-ego.fandom.com/wiki/Special:Contribs/RustyChroma"
        },
        "fields": [],
        "color": 9306112
      }
    ]
  },
  {
    "timestamp": 1780282116355,
    "embeds": [
      {
        "title": "Follower ( +6)",
        "description": "\\[IPE-NEXT\\] Quick edit",
        "author": {
          "name": "RustyChroma",
          "url": "https://alter-ego.fandom.com/wiki/Special:Contribs/RustyChroma"
        },
        "fields": [],
        "color": 35840
      }
    ]
  },
  {
    "timestamp": 1780282013794,
    "embeds": [
      {
        "title": "Follower ( -16)",
        "description": "\\[IPE-NEXT\\] Quick edit",
        "author": {
          "name": "RustyChroma",
          "url": "https://alter-ego.fandom.com/wiki/Special:Contribs/RustyChroma"
        },
        "fields": [],
        "color": 9175040
      }
    ]
  },
  {
    "timestamp": 1780281925709,
    "embeds": [
      {
        "title": "Follower ( -606)",
        "description": "\\[IPE-NEXT\\] Quick edit",
        "author": {
          "name": "RustyChroma",
          "url": "https://alter-ego.fandom.com/wiki/Special:Contribs/RustyChroma"
        },
        "fields": [],
        "color": 9895936
      }
    ]
  },
  {
    "timestamp": 1780281757253,
    "embeds": [
      {
        "title": "Follower ( +53)",
        "description": "No description provided",
        "author": {
          "name": "RustyChroma",
          "url": "https://alter-ego.fandom.com/wiki/Special:Contribs/RustyChroma"
        },
        "fields": [],
        "color": 36096
      }
    ]
  }
]